pyPreprocessing/__init__.py
pyPreprocessing/baseline_correction.py
pyPreprocessing/smoothing.py
pyPreprocessing/transform.py
pyPreprocessing-0.0.2.dist-info/LICENSE
pyPreprocessing-0.0.2.dist-info/METADATA
pyPreprocessing-0.0.2.dist-info/WHEEL
pyPreprocessing-0.0.2.dist-info/dependency_links.txt
pyPreprocessing-0.0.2.dist-info/top_level.txt
pyPreprocessing-0.0.2.dist-info/RECORD
