Metadata-Version: 2.1
Name: pyPreprocessing
Version: 0.0.2
Summary: package preprocessing of datasets, especially from spectroscopy
Home-page: https://github.com/AlexanderSouthan/pyPreprocessing
Author: Alexander Southan
Author-email: alexander.southan@web.de
Project-URL: Bug Tracker, https://github.com/AlexanderSouthan/pyPreprocessing/issues
Classifier: Programming Language :: Python :: 3
Classifier: License :: OSI Approved :: MIT License
Classifier: Operating System :: OS Independent
Requires-Python: >=3.6
License-File: LICENSE
Requires-Dist: numpy
Requires-Dist: pandas
Requires-Dist: scipy
Requires-Dist: matplotlib
Requires-Dist: scikit-learn
Requires-Dist: tqdm
